MANIFEST.in
setup.py
src/web_gamepad/__init__.py
src/web_gamepad/gamepad_server.py
src/web_gamepad.egg-info/PKG-INFO
src/web_gamepad.egg-info/SOURCES.txt
src/web_gamepad.egg-info/dependency_links.txt
src/web_gamepad.egg-info/not-zip-safe
src/web_gamepad.egg-info/requires.txt
src/web_gamepad.egg-info/top_level.txt
src/web_gamepad/core/__init__.py
src/web_gamepad/core/views.py
src/web_gamepad/gamepad/__init__.py
src/web_gamepad/gamepad/game_factory.py
src/web_gamepad/gamepad/gamepad_controller.py
src/web_gamepad/gamepad/unit.py
src/web_gamepad/static/css/style.css
src/web_gamepad/static/images/background.jpg
src/web_gamepad/static/images/bullet_hero.png
src/web_gamepad/static/images/hero_1_black.png
src/web_gamepad/static/images/hero_1_blue.png
src/web_gamepad/static/images/hero_1_green.png
src/web_gamepad/static/images/hero_1_pink.png
src/web_gamepad/static/images/hero_1_red.png
src/web_gamepad/static/images/hero_1_white.png
src/web_gamepad/static/images/hero_2_black.png
src/web_gamepad/static/images/hero_2_blue.png
src/web_gamepad/static/images/hero_2_green.png
src/web_gamepad/static/images/hero_2_pink.png
src/web_gamepad/static/images/hero_2_red.png
src/web_gamepad/static/images/hero_2_white.png
src/web_gamepad/static/images/invader1.png
src/web_gamepad/static/images/invader2.png
src/web_gamepad/static/images/invader3.png
src/web_gamepad/static/js/game.js
src/web_gamepad/static/js/web_socket.js
src/web_gamepad/templates/base.html
src/web_gamepad/templates/game.html
src/web_gamepad/templates/gamepad.html
src/web_gamepad/templates/index.html